<?xml version="1.0" encoding="utf-8"?>
<search>
  
  
  
  <entry>
    <title>The dream of future</title>
    <link href="/2022/03/22/1/"/>
    <url>/2022/03/22/1/</url>
    
    <content type="html"><![CDATA[<p>什么都得自己提前去准备好，包括对自己的认识，以及世界的认识。在大学有<a href="https://ncre-bm.neea.edu.cn/">计算机考试</a>，<a href="https://cet-bm.neea.edu.cn/">CET考试</a>，<a href="https://pets.neea.edu.cn/">PETS</a>，<a href="http://cicpa.org.cn/ztzl1/exam/kswzbmlj/">CPA</a>。</p><p>当然不是为了考试，计算机我是不打算学的，湘湘有段时间一直问我以后干什么，我没给她答案，因为我不喜欢计算机。我希望可以多去经历，多去给别人试，其实这一生真的很多的虚伪，一个人的一生在虚伪中度过是最悲惨的事情，因为他没有活过。我就是这样啊，前十几年的记忆很压抑，基本全部丢失了，一下子长大了。我不想像伊凡伊里奇一样在死后在自己的葬礼上听人们来唏嘘我的灵魂，那我宁可不要举办葬礼。当然这个世界并不欢迎好人，并不欢迎博物学家。我尝试喜欢一些比较宽口径的比如说可以去当个博物馆，图书馆，自由职业类的，这些能让我真正活过来又不死过去。就算选这些不也是为了实现价值的快乐吗？人这一生寻求快乐，寻求意义是我们反抗无意义的一纸荒唐言。</p><p>为了真正的活着，也不能习惯于活着，不断的接受刺激，等待死亡，像刚出生时经历着意识变换。如<a href="https://plato.stanford.edu/entries/emerson/">Ralph Waldo Emerson</a>所想，保持幼稚，保持谦逊。</p><p>不要像一个道士一样嗡嗡嗡，来点实际的，你想做什么？你的生活有保障吗？说到底，我是没有像湘湘一样的为社会奉献的动力的，我有一些自私，是的，但只要私有制存在，谁不自私呢？我想做个生活区博主，这很伟大吧。当然也很轻松，平时只是想过个精打细算的生活，在山东威海或者日照有个房子，那里还没有自然灾害，海滨小镇，打滚晒太阳！</p><p>平庸自私无聊的人生，在科学家看来我简直是个不该活在世界上的人，他们痛恨我没有精密和想象力的大脑，也许不会，他们也宣扬无知？我不会摆烂，但想到不能与爱因斯坦，冯诺依曼，牛顿，肩并肩，不能成为一个横空出世的普朗克发现个量子力学而高兴，有点叹气？牛顿要是活着该作何感想对于普朗克？他是嫉妒还是高兴呢？不得而知。</p><p>生活，没让我狂热，但是让我这个要死的人不能死，让活的人又生不如死。我抗争，满足我的需求，追求卓越，夜晚，食欲，爱欲，性欲。看到这里你还会讨厌赞扬苦难吗？我们改变不了我们受过的苦难，必须得继续往下走，当死亡的预警出现在我们面前，我们最好珍惜当下。死亡曼妙。满足即为多巴胺分泌，而痛苦快乐我们全部上瘾了。</p><p>说了那么多意义无非是侃侃而谈，而是谨记生活本质，真正的活着，真正成为人，血肉骨头屎尿人。</p>]]></content>
    
    
    <categories>
      
      <category>Opinions</category>
      
    </categories>
    
    
    <tags>
      
      <tag>Plans</tag>
      
    </tags>
    
  </entry>
  
  
  
  
</search>
